python_snarks/__init__.py
python_snarks/py.typed
python_snarks/arithmetic/__init__.py
python_snarks/arithmetic/bn128.py
python_snarks/arithmetic/curve.py
python_snarks/arithmetic/curve_point.py
python_snarks/arithmetic/field.py
python_snarks/arithmetic/field2.py
python_snarks/arithmetic/field3.py
python_snarks/arithmetic/field_elements.py
python_snarks/arithmetic/field_polynomial.py
python_snarks/arithmetic/field_properties.py
python_snarks/arithmetic/utils.py
python_snarks/groth16/__init__.py
python_snarks/groth16/contract.py
python_snarks/groth16/groth_prover.py
python_snarks/groth16/groth_setup.py
python_snarks/groth16/groth_verifier.py
python_snarks/groth16/witness_calculator.py
python_snarks/r1csfile/__init__.py
python_snarks/r1csfile/r1cs_file.py
python_snarks-0.0.3.dist-info/LICENSE
python_snarks-0.0.3.dist-info/METADATA
python_snarks-0.0.3.dist-info/WHEEL
python_snarks-0.0.3.dist-info/top_level.txt
python_snarks-0.0.3.dist-info/RECORD
