Metadata-Version: 2.1
Name: python-snarks
Version: 0.0.3
Summary: python_snarks
Home-page: https://github.com/Onther-Tech/python-snarks
Author: Onther Inc.
Author-email: info@onther.io
License: GPLv3
Keywords: snarks
Platform: UNKNOWN
Classifier: Programming Language :: Python :: 3
Classifier: Programming Language :: Python :: 3.6
Classifier: Programming Language :: Python :: 3.7
Classifier: Programming Language :: Python :: 3.8
Classifier: License :: OSI Approved :: GNU General Public License v3 (GPLv3)
Requires-Python: >=3.6,<4
Requires-Dist: fnv (>=0.2.0)
Requires-Dist: wasmer (>=1.0.0a3)
Requires-Dist: wasmer-compiler-cranelift (>=1.0.0a3)
Provides-Extra: dev
Requires-Dist: bumpversion ; extra == 'dev'
Requires-Dist: pytest (>=6.1.2) ; extra == 'dev'
